{
    "job": {
        "setting": {
            "speed": {
                "channel": 10,
                "record": -1,
                "byte": -1
            },
            "errorLimit": {
                "record": 0
            }
        },
        "content": [
            {
                "reader": {
                    "name": "sqlserverreader",
                    "parameter": {
                        "username": "sa",
                        "password": "abc123!@#",
                        "column": [
                            "[TASK_ID]",
                            "[B_SNO]",
                            "[BUSI_CODE]",
                            "[OPER_TIME]",
                            "[VAR_NAME]",
                            "[VAR_VALUE]",
                            "[HANDLER]",
                            "[REMARK]",
                            "[NODE_NAME]",
                            "[NODE_KEY]",
                            "[OP_START_TIME]",
                            "[NODE_RESULT]",
                            "[REJECT_LVL]"
                        ],
                        "splitPk": "",
                        "connection": [
                            {
                                "table": [
                                    "YGT.dbo.OPP_BUSI_NODE"
                                ],
                                "jdbcUrl": [
                                    "jdbc:sqlserver://10.81.2.110:1433;DatabaseName=YGT;"
                                ]
                            }
                        ]
                    }
                },
                "writer": {
                    "name": "postgresqlwriter",
                    "parameter": {
                        "username": "ygt",
                        "password": "Testygt123!@#",
                        "column": [
                            "\"task_id\"",
                            "\"b_sno\"",
                            "\"busi_code\"",
                            "\"oper_time\"",
                            "\"var_name\"",
                            "\"var_value\"",
                            "\"handler\"",
                            "\"remark\"",
                            "\"node_name\"",
                            "\"node_key\"",
                            "\"op_start_time\"",
                            "\"node_result\"",
                            "\"reject_lvl\""
                        ],
                        "preSql": [
                            "TRUNCATE TABLE ygt.ygt.opp_busi_node"
                        ],
                        "connection": [
                            {
                                "jdbcUrl": "jdbc:postgresql://10.201.65.24:30100/ygt",
                                "table": [
                                    "ygt.ygt.opp_busi_node"
                                ]
                            }
                        ]
                    }
                }
            }
        ]
    }
}