{
    "job": {
        "setting": {
            "speed": {
                "channel": 10,
                "record": -1,
                "byte": -1
            },
            "errorLimit": {
                "record": 0
            }
        },
        "content": [
            {
                "reader": {
                    "name": "sqlserverreader",
                    "parameter": {
                        "username": "sa",
                        "password": "abc123!@#",
                        "column": [
                            "[RTRES_ID]",
                            "[RTRES_NAME]",
                            "[RTRES_TYPE]",
                            "[RTRES_DATA]",
                            "[DATA_TYPE]",
                            "[RIGHT_TYPES]",
                            "[SHOW_TYPE]",
                            "[RTRES_ORD]"
                        ],
                        "splitPk": "",
                        "connection": [
                            {
                                "table": [
                                    "YGT.dbo.UPM_SYS_RTRES_BAK"
                                ],
                                "jdbcUrl": [
                                    "jdbc:sqlserver://10.81.2.110:1433;DatabaseName=YGT;"
                                ]
                            }
                        ]
                    }
                },
                "writer": {
                    "name": "postgresqlwriter",
                    "parameter": {
                        "username": "ygt",
                        "password": "Testygt123!@#",
                        "column": [
                            "\"rtres_id\"",
                            "\"rtres_name\"",
                            "\"rtres_type\"",
                            "\"rtres_data\"",
                            "\"data_type\"",
                            "\"right_types\"",
                            "\"show_type\"",
                            "\"rtres_ord\""
                        ],
                        "preSql": [
                            "TRUNCATE TABLE ygt.ygt.upm_sys_rtres_bak"
                        ],
                        "connection": [
                            {
                                "jdbcUrl": "jdbc:postgresql://10.201.65.24:30100/ygt",
                                "table": [
                                    "ygt.ygt.upm_sys_rtres_bak"
                                ]
                            }
                        ]
                    }
                }
            }
        ]
    }
}